texi/__init__.py
texi/apps/__init__.py
texi/apps/classification/__init__.py
texi/apps/classification/train.py
texi/apps/ner/__init__.py
texi/apps/ner/conlleval.pl
texi/apps/ner/data.py
texi/apps/ner/eval.py
texi/apps/ner/span_utils.py
texi/apps/ner/templates/entity_examples.html
texi/apps/ner/templates/relation_examples.html
texi/apps/ner/utils.py
texi/apps/ner/visualization.py
texi/apps/text_matching/__init__.py
texi/apps/text_matching/train.py
texi/datasets/__init__.py
texi/datasets/classification.py
texi/datasets/dataset.py
texi/datasets/question_answering.py
texi/datasets/text.py
texi/datasets/translation.py
texi/embedding.py
texi/metrics.py
texi/preprocessing.py
texi/py.typed
texi/pytorch/__init__.py
texi/pytorch/dataset/__init__.py
texi/pytorch/dataset/collator.py
texi/pytorch/dataset/plm_collator.py
texi/pytorch/metrics/__init__.py
texi/pytorch/metrics/general_accuracy.py
texi/pytorch/metrics/mean_reciprocal_rank.py
texi/pytorch/metrics/metrics.py
texi/pytorch/metrics/ner_metrics.py
texi/pytorch/metrics/re_metrics.py
texi/pytorch/metrics/sequence_labeling_metrics.py
texi/pytorch/models/__init__.py
texi/pytorch/models/classification.py
texi/pytorch/models/question_answering.py
texi/pytorch/models/sequence_labeling.py
texi/pytorch/models/spert/__init__.py
texi/pytorch/models/spert/dataset.py
texi/pytorch/models/spert/loss.py
texi/pytorch/models/spert/model.py
texi/pytorch/models/spert/prediction.py
texi/pytorch/models/spert/sampler.py
texi/pytorch/models/spert/training.py
texi/pytorch/models/text_matching.py
texi/tagger/__init__.py
texi/tagger/sequence_labeling.py
texi/vocab.py
texi-0.2.3.dist-info/WHEEL
texi-0.2.3.dist-info/METADATA
texi-0.2.3.dist-info/RECORD
